README.md
setup.py
graphSimilarity/__init__.py
graphSimilarity/distance_functions.py
graphSimilarity/graph.py
graphSimilarity/graph_generator.py
graphSimilarity/graph_generator_2.py
graphSimilarity/kernel_kmeans.py
graphSimilarity/kernel_methods.py
graphSimilarity/kmeans_init.py
graphSimilarity/sd_kmeans.py
graphSimilarity/utils.py
graphSimilarity.egg-info/PKG-INFO
graphSimilarity.egg-info/SOURCES.txt
graphSimilarity.egg-info/dependency_links.txt
graphSimilarity.egg-info/requires.txt
graphSimilarity.egg-info/top_level.txt