Metadata-Version: 1.0
Name: graphSimilarity
Version: 0.1.0
Summary: Graph Distance Measures and Clustering
Home-page: UNKNOWN
Author: Ivan Kyosev
Author-email: 2092065k@student.gla.ac.uk
License: GPL
Platform: UNKNOWN
